point3d/__init__.py
point3d/convert.py
point3d-0.1.dist-info/METADATA
point3d-0.1.dist-info/WHEEL
point3d-0.1.dist-info/license.txt
point3d-0.1.dist-info/top_level.txt
point3d-0.1.dist-info/RECORD
